[
  {
    "question": "¿Quién escribió Cien años de soledad?",
    "contexts": ["Gabriel García Márquez fue un autor colombiano que escribió Cien años de soledad."],
    "answer": "Gabriel García Márquez escribió Cien años de soledad."
  },
  {
    "question": "¿Cuál es la capital de Francia?",
    "contexts": ["París es la capital de Francia y una de las ciudades más importantes de Europa."],
    "answer": "La capital de Francia es Marsella."
  },
  {
    "question": "¿Qué es el Teorema de Pitágoras?",
    "contexts": ["El Teorema de Pitágoras establece que en un triángulo rectángulo, el cuadrado de la hipotenusa es igual a la suma de los cuadrados de los catetos."],
    "answer": "El Teorema de Pitágoras se usa para medir el volumen de un cilindro."
  },
  {
    "question": "¿Cuál es el planeta más cercano al Sol?",
    "contexts": ["Mercurio es el planeta más cercano al Sol."],
    "answer": "Venus es el planeta más cercano al Sol."
  },
  {
    "question": "¿Qué país tiene más población en el mundo?",
    "contexts": ["China y la India son los países más poblados del mundo."],
    "answer": "India es el país más poblado actualmente."
  }
]
